lib/rclone
pibackup/__init__.py
pibackup/__version__.py
pibackup/app.py
pibackup/config.json
pibackup/config.py
pibackup/helpers.py
pibackup/pibackup-conf.py
pibackup/test.py
pibackup-0.0.14.dist-info/DESCRIPTION.rst
pibackup-0.0.14.dist-info/METADATA
pibackup-0.0.14.dist-info/RECORD
pibackup-0.0.14.dist-info/WHEEL
pibackup-0.0.14.dist-info/entry_points.txt
pibackup-0.0.14.dist-info/metadata.json
pibackup-0.0.14.dist-info/top_level.txt
