Metadata-Version: 2.0
Name: pibackup
Version: 0.0.14
Summary: Scheduled cloud backup for Raspberry Pi running smart home systems like fhem or iobroker
Home-page: UNKNOWN
Author: p1ppo
Author-email: UNKNOWN
License: MIT
Platform: UNKNOWN
Requires-Dist: schedule
Requires-Dist: python-crontab
